dtorch/__init__.py
dtorch/dataset.py
dtorch/derivatives.py
dtorch/einops.py
dtorch/functionnal.py
dtorch/jtensors.py
dtorch/loss.py
dtorch/nn.py
dtorch/operation_class.py
dtorch/operations.py
dtorch/optim.py
dtorch/typing.py
dtorchtext/datasets.py
dtorchtext/models.py
dtorchtree/datasets.py
dtorchtree/models.py
dtorchvision/datasets.py
dtorchvision/models.py
dtorch-0.0.7.dist-info/LICENSE
dtorch-0.0.7.dist-info/METADATA
dtorch-0.0.7.dist-info/WHEEL
dtorch-0.0.7.dist-info/top_level.txt
dtorch-0.0.7.dist-info/RECORD
