Metadata-Version: 2.1
Name: dtorch
Version: 0.0.7
Summary: A scientific package made a fellow student
Author-email: Just1truc <hyppoduc@gmail.com>
Project-URL: Homepage, https://github.com/Just1truc/dtorch
Project-URL: Bug Tracker, https://github.com/Just1truc/dtorch/issues
Classifier: Programming Language :: Python :: 3
Classifier: License :: OSI Approved :: MIT License
Classifier: Operating System :: OS Independent
Requires-Python: >=3.10
License-File: LICENSE
Requires-Dist: requests
Requires-Dist: numpy
